[
  {
    "line": "101",
    "status": "301",
    "source": "/begrippen/tweede-kamer/",
    "target": "https://schoolwoorden.nl/begrip/tweede-kamer/"
  },
  {
    "line": "102",
    "status": "301",
    "source": "/begrippen/eerste-kamer/",
    "target": "https://schoolwoorden.nl/begrip/eerste-kamer/"
  },
  {
    "line": "103",
    "status": "301",
    "source": "/begrippen/parlement/",
    "target": "https://schoolwoorden.nl/begrip/parlement/"
  },
  {
    "line": "104",
    "status": "301",
    "source": "/begrippen/begroting/",
    "target": "https://schoolwoorden.nl/begrip/begroting/"
  },
  {
    "line": "105",
    "status": "301",
    "source": "/begrippen/algemene-beschouwingen/",
    "target": "https://schoolwoorden.nl/begrip/algemene-beschouwingen/"
  },
  {
    "line": "106",
    "status": "301",
    "source": "/begrippen/burgemeester/",
    "target": "https://schoolwoorden.nl/begrip/burgemeester/"
  },
  {
    "line": "107",
    "status": "301",
    "source": "/begrippen/college-burgemeester-en-wethouders/",
    "target": "https://schoolwoorden.nl/begrip/college-van-burgemeester-en-wethouders"
  },
  {
    "line": "108",
    "status": "301",
    "source": "/begrippen/coalitiepartijen/",
    "target": "https://schoolwoorden.nl/begrip/coalitie/"
  },
  {
    "line": "109",
    "status": "301",
    "source": "/begrippen/commissaris-van-de-koning/",
    "target": "https://schoolwoorden.nl/begrip/commissaris-van-de-koning/"
  },
  {
    "line": "110",
    "status": "301",
    "source": "/begrippen/dictatuur/",
    "target": "https://schoolwoorden.nl/begrip/dictatuur/"
  },
  {
    "line": "111",
    "status": "301",
    "source": "/begrippen/gemeenteraad/",
    "target": "https://schoolwoorden.nl/begrip/gemeenteraad/"
  },
  {
    "line": "112",
    "status": "301",
    "source": "/begrippen/directe-verkiezingen/",
    "target": "https://schoolwoorden.nl/begrip/directe-verkiezingen/"
  },
  {
    "line": "113",
    "status": "301",
    "source": "/begrippen/fractievoorzitter/",
    "target": "https://schoolwoorden.nl/begrip/fractievoorzitter/"
  },
  {
    "line": "114",
    "status": "301",
    "source": "/begrippen/gedeputeerde-staten/",
    "target": "https://schoolwoorden.nl/begrip/gedeputeerde-staten/"
  },
  {
    "line": "115",
    "status": "301",
    "source": "/begrippen/grondrechten/",
    "target": "https://schoolwoorden.nl/begrip/grondrechten/"
  },
  {
    "line": "116",
    "status": "301",
    "source": "/begrippen/indirecte-verkiezingen/",
    "target": "https://schoolwoorden.nl/begrip/indirecte-verkiezingen/"
  },
  {
    "line": "117",
    "status": "301",
    "source": "/begrippen/kabinet/",
    "target": "https://schoolwoorden.nl/begrip/kabinet/"
  },
  {
    "line": "118",
    "status": "301",
    "source": "/begrippen/kabinetscrisis/",
    "target": "https://schoolwoorden.nl/begrip/kabinetscrisis/"
  },
  {
    "line": "119",
    "status": "301",
    "source": "/begrippen/kabinetsformatie/",
    "target": "https://schoolwoorden.nl/begrip/kabinetsformatie/"
  },
  {
    "line": "120",
    "status": "301",
    "source": "/begrippen/kiesdeler/",
    "target": "https://schoolwoorden.nl/begrip/kiesdeler/"
  },
  {
    "line": "121",
    "status": "301",
    "source": "/begrippen/machtenscheiding/",
    "target": "https://schoolwoorden.nl/begrip/machtenscheiding/"
  },
  {
    "line": "122",
    "status": "301",
    "source": "/begrippen/miljoenennota/",
    "target": "https://schoolwoorden.nl/begrip/miljoenennota/"
  },
  {
    "line": "123",
    "status": "301",
    "source": "/begrippen/christelijke-stroming/",
    "target": "https://schoolwoorden.nl/begrip/christelijke-stroming/"
  },
  {
    "line": "124",
    "status": "301",
    "source": "/begrippen/ministeriele-verantwoordelijkheid/",
    "target": "https://schoolwoorden.nl/begrip/ministeriele-verantwoordelijkheid/"
  },
  {
    "line": "125",
    "status": "301",
    "source": "/begrippen/minister-president/",
    "target": "https://schoolwoorden.nl/begrip/minister-president/"
  },
  {
    "line": "126",
    "status": "301",
    "source": "/begrippen/parlementaire-democratie/",
    "target": "https://schoolwoorden.nl/begrip/parlementaire-democratie/"
  },
  {
    "line": "127",
    "status": "301",
    "source": "/begrippen/parlementair-jaar/",
    "target": "https://schoolwoorden.nl/begrip/parlementair-jaar/"
  },
  {
    "line": "128",
    "status": "301",
    "source": "/begrippen/provinciale-staten/",
    "target": "https://schoolwoorden.nl/begrip/provinciale-staten/"
  },
  {
    "line": "129",
    "status": "301",
    "source": "/begrippen/rechterlijke-macht/",
    "target": "https://schoolwoorden.nl/begrip/rechterlijke-macht/"
  },
  {
    "line": "130",
    "status": "301",
    "source": "/begrippen/rechtsstaat/",
    "target": "https://schoolwoorden.nl/begrip/rechtsstaat/"
  },
  {
    "line": "131",
    "status": "301",
    "source": "/begrippen/recht-van-initiatief/",
    "target": "https://schoolwoorden.nl/begrip/recht-van-initiatief/"
  },
  {
    "line": "132",
    "status": "301",
    "source": "/begrippen/recht-van-amendement/",
    "target": "https://schoolwoorden.nl/begrip/recht-van-amendement/"
  },
  {
    "line": "133",
    "status": "301",
    "source": "/begrippen/recht-van-motie/",
    "target": "https://schoolwoorden.nl/begrip/recht-van-motie/"
  },
  {
    "line": "134",
    "status": "301",
    "source": "/begrippen/recht-van-enquete/",
    "target": "https://schoolwoorden.nl/begrip/recht-van-enquete/"
  },
  {
    "line": "135",
    "status": "301",
    "source": "/begrippen/reageerakkoord/",
    "target": "https://schoolwoorden.nl/begrip/regeerakkoord/"
  },
  {
    "line": "136",
    "status": "301",
    "source": "/begrippen/collegeakkoord/",
    "target": "https://schoolwoorden.nl/begrip/collegeakkoord/"
  },
  {
    "line": "137",
    "status": "301",
    "source": "/begrippen/regering/",
    "target": "https://schoolwoorden.nl/begrip/regering/"
  },
  {
    "line": "138",
    "status": "301",
    "source": "/begrippen/staatshoofd/",
    "target": "https://schoolwoorden.nl/begrip/staatshoofd/"
  },
  {
    "line": "139",
    "status": "301",
    "source": "/begrippen/staatssecretaris/",
    "target": "https://schoolwoorden.nl/begrip/staatssecretaris/"
  },
  {
    "line": "140",
    "status": "301",
    "source": "/begrippen/troonrede/",
    "target": "https://schoolwoorden.nl/begrip/troonrede/"
  },
  {
    "line": "141",
    "status": "301",
    "source": "/begrippen/trias-politica/",
    "target": "https://schoolwoorden.nl/begrip/trias-politica/"
  },
  {
    "line": "142",
    "status": "301",
    "source": "/begrippen/uitvoerende-macht/",
    "target": "https://schoolwoorden.nl/begrip/uitvoerende-macht/"
  },
  {
    "line": "143",
    "status": "301",
    "source": "/begrippen/verordening/",
    "target": "https://schoolwoorden.nl/begrip/verordening/"
  },
  {
    "line": "144",
    "status": "301",
    "source": "/begrippen/volksvertegenwoordigers/",
    "target": "https://schoolwoorden.nl/begrip/volksvertegenwoordigers/"
  },
  {
    "line": "145",
    "status": "301",
    "source": "/begrippen/wetgevende-macht/",
    "target": "https://schoolwoorden.nl/begrip/wetgevende-macht/"
  },
  {
    "line": "146",
    "status": "301",
    "source": "/begrippen/vrije-verkiezingen/",
    "target": "https://schoolwoorden.nl/begrip/vrije-verkiezingen/"
  },
  {
    "line": "147",
    "status": "301",
    "source": "/begrippen/recht-van-budget/",
    "target": "https://schoolwoorden.nl/begrip/recht-van-budget/"
  },
  {
    "line": "148",
    "status": "301",
    "source": "/begrippen/constitutionele-monarchie/",
    "target": "https://schoolwoorden.nl/begrip/constitutionele-monarchie/"
  },
  {
    "line": "149",
    "status": "301",
    "source": "/begrippen/geheim-van-het-paleid/",
    "target": "https://schoolwoorden.nl/begrip/geheim-van-het-paleis/"
  },
  {
    "line": "150",
    "status": "301",
    "source": "/begrippen/europese-gemeenschap-kolen-en-staal/",
    "target": "https://schoolwoorden.nl/begrip/europese-gemeenschap-voor-kolen-en-staal"
  },
  {
    "line": "151",
    "status": "301",
    "source": "/begrippen/europese-gemeenschap/",
    "target": "https://schoolwoorden.nl/begrip/europese-gemeenschap/"
  },
  {
    "line": "152",
    "status": "301",
    "source": "/begrippen/europese-unie/",
    "target": "https://schoolwoorden.nl/begrip/europese-unie/"
  },
  {
    "line": "153",
    "status": "301",
    "source": "/begrippen/europese-parlement/",
    "target": "https://schoolwoorden.nl/begrip/europees-parlement/"
  },
  {
    "line": "154",
    "status": "301",
    "source": "/begrippen/europese-commissie/",
    "target": "https://schoolwoorden.nl/begrip/europese-commissie/"
  },
  {
    "line": "155",
    "status": "301",
    "source": "/begrippen/raad-europese-unie/",
    "target": "https://schoolwoorden.nl/begrip/raad-van-de-europese-unie"
  },
  {
    "line": "156",
    "status": "301",
    "source": "/begrippen/europese-raad/",
    "target": "https://schoolwoorden.nl/begrip/europese-raad/"
  },
  {
    "line": "157",
    "status": "301",
    "source": "/begrippen/politiek-probleem/",
    "target": "https://schoolwoorden.nl/begrip/politiek-probleem/"
  },
  {
    "line": "158",
    "status": "301",
    "source": "/begrippen/politieke-agenda/",
    "target": "https://schoolwoorden.nl/begrip/politieke-agenda/"
  },
  {
    "line": "159",
    "status": "301",
    "source": "/begrippen/beleidsvoorbereiding/",
    "target": "https://schoolwoorden.nl/begrip/beleidsvoorbereiding/"
  },
  {
    "line": "160",
    "status": "301",
    "source": "/begrippen/lobbyen/",
    "target": "https://schoolwoorden.nl/begrip/lobbyen/"
  },
  {
    "line": "161",
    "status": "301",
    "source": "/begrippen/referendum/",
    "target": "https://schoolwoorden.nl/begrip/referendum/"
  },
  {
    "line": "162",
    "status": "301",
    "source": "/begrippen/dereguleren/",
    "target": "https://schoolwoorden.nl/begrip/dereguleren/"
  },
  {
    "line": "163",
    "status": "301",
    "source": "/begrippen/rentmeesterschap/",
    "target": "https://schoolwoorden.nl/begrip/rentmeesterschap/"
  },
  {
    "line": "164",
    "status": "301",
    "source": "/begrippen/waarden/",
    "target": "https://schoolwoorden.nl/begrip/waarden/"
  },
  {
    "line": "165",
    "status": "301",
    "source": "/begrippen/normen/",
    "target": "https://schoolwoorden.nl/begrip/normen/"
  },
  {
    "line": "166",
    "status": "301",
    "source": "/begrippen/wet/",
    "target": "https://schoolwoorden.nl/begrip/wet/"
  },
  {
    "line": "167",
    "status": "301",
    "source": "/begrippen/criminaliteit/",
    "target": "https://schoolwoorden.nl/begrip/criminaliteit/"
  },
  {
    "line": "168",
    "status": "301",
    "source": "/begrippen/wetboek-van-strafrecht/",
    "target": "https://schoolwoorden.nl/begrip/wetboek-van-strafrecht/"
  },
  {
    "line": "169",
    "status": "301",
    "source": "/begrippen/overtredingen/",
    "target": "https://schoolwoorden.nl/begrip/overtreding/"
  },
  {
    "line": "170",
    "status": "301",
    "source": "/begrippen/misdrijven/",
    "target": "https://schoolwoorden.nl/begrip/misdrijf/"
  },
  {
    "line": "171",
    "status": "301",
    "source": "/begrippen/delicten/",
    "target": "https://schoolwoorden.nl/begrip/delict/"
  },
  {
    "line": "172",
    "status": "301",
    "source": "/begrippen/materiele-schade/",
    "target": "https://schoolwoorden.nl/begrip/materiele-gevolgen/"
  },
  {
    "line": "173",
    "status": "301",
    "source": "/begrippen/immateriele-schade/",
    "target": "https://schoolwoorden.nl/begrip/immateriele-gevolgen/"
  },
  {
    "line": "174",
    "status": "301",
    "source": "/begrippen/sector-kanton/",
    "target": "https://schoolwoorden.nl/begrip/sector-kanton/"
  },
  {
    "line": "175",
    "status": "301",
    "source": "/begrippen/sector-strafrecht/",
    "target": "https://schoolwoorden.nl/begrip/sector-strafrecht/"
  },
  {
    "line": "176",
    "status": "301",
    "source": "/begrippen/sector-civiel/",
    "target": "https://schoolwoorden.nl/begrip/sector-civiel/"
  },
  {
    "line": "177",
    "status": "301",
    "source": "/begrippen/sector-bestuursrecht/",
    "target": "https://schoolwoorden.nl/begrip/sector-bestuursrecht/"
  },
  {
    "line": "178",
    "status": "301",
    "source": "/begrippen/requisitoir/",
    "target": "https://schoolwoorden.nl/begrip/requisitoir/"
  },
  {
    "line": "179",
    "status": "301",
    "source": "/begrippen/pleidooi/",
    "target": "https://schoolwoorden.nl/begrip/pleidooi/"
  },
  {
    "line": "180",
    "status": "301",
    "source": "/begrippen/bureau-reclassering/",
    "target": "https://schoolwoorden.nl/begrip/bureau-reclassering/"
  },
  {
    "line": "181",
    "status": "301",
    "source": "/begrippen/officier-van-justitie/",
    "target": "https://schoolwoorden.nl/begrip/officier-van-justitie/"
  },
  {
    "line": "182",
    "status": "301",
    "source": "/begrippen/recidiveren/",
    "target": "https://schoolwoorden.nl/begrip/recidiveren/"
  },
  {
    "line": "183",
    "status": "301",
    "source": "/begrippen/etikettering/",
    "target": "https://schoolwoorden.nl/begrip/etikettering/"
  },
  {
    "line": "184",
    "status": "301",
    "source": "/begrippen/normvervaging/",
    "target": "https://schoolwoorden.nl/begrip/normvervaging/"
  },
  {
    "line": "185",
    "status": "301",
    "source": "/begrippen/klassenjustitie/",
    "target": "https://schoolwoorden.nl/begrip/klassenjustitie/"
  },
  {
    "line": "186",
    "status": "301",
    "source": "/begrippen/witteboordencriminaliteit/",
    "target": "https://schoolwoorden.nl/begrip/witteboordencriminaliteit/"
  },
  {
    "line": "187",
    "status": "301",
    "source": "/begrippen/indoctrinatie/",
    "target": "https://schoolwoorden.nl/begrip/indoctrinatie/"
  },
  {
    "line": "188",
    "status": "301",
    "source": "/begrippen/manipulatie/",
    "target": "https://schoolwoorden.nl/begrip/manipulatie/"
  },
  {
    "line": "189",
    "status": "301",
    "source": "/begrippen/referentiekader/",
    "target": "https://schoolwoorden.nl/begrip/referentiekader/"
  },
  {
    "line": "190",
    "status": "301",
    "source": "/begrippen/regeerakkoord/",
    "target": "https://schoolwoorden.nl/begrip/regeerakkoord/"
  },
  {
    "line": "191",
    "status": "301",
    "source": "/begrippen/rechtbank/",
    "target": "https://schoolwoorden.nl/begrip/rechtbank/"
  },
  {
    "line": "192",
    "status": "301",
    "source": "/begrippen/gerechtshof/",
    "target": "https://schoolwoorden.nl/begrip/gerechtshof/"
  },
  {
    "line": "193",
    "status": "301",
    "source": "/begrippen/hoge-raad/",
    "target": "https://schoolwoorden.nl/begrip/hoge-raad/"
  },
  {
    "line": "194",
    "status": "301",
    "source": "/begrippen/voorzitter-tweede-kamer/",
    "target": "https://schoolwoorden.nl/begrip/voorzitter-van-de-tweede-kamer"
  },
  {
    "line": "195",
    "status": "301",
    "source": "/begrippen/wegenverkeerswet/",
    "target": "https://schoolwoorden.nl/begrip/wegenverkeerswet/"
  },
  {
    "line": "196",
    "status": "301",
    "source": "/begrippen/wet-economische-delicten/",
    "target": "https://schoolwoorden.nl/begrip/wet-op-de-economische-delicten/"
  },
  {
    "line": "197",
    "status": "301",
    "source": "/begrippen/opiuwet/",
    "target": "https://schoolwoorden.nl/begrip/opiumwet/"
  },
  {
    "line": "198",
    "status": "301",
    "source": "/begrippen/multi-step-flow-theorie/",
    "target": "https://schoolwoorden.nl/begrip/multistepflowtheorie/"
  },
  {
    "line": "199",
    "status": "301",
    "source": "/begrippen/injectienaaldtheorie/",
    "target": "https://schoolwoorden.nl/begrip/injectienaaldtheorie/"
  },
  {
    "line": "200",
    "status": "301",
    "source": "/begrippen/agendatheorie/",
    "target": "https://schoolwoorden.nl/begrip/agendatheorie/"
  },
  {
    "line": "201",
    "status": "301",
    "source": "/begrippen/maatschappelijke-positie/",
    "target": "https://schoolwoorden.nl/begrip/maatschappelijke-positie/"
  },
  {
    "line": "202",
    "status": "301",
    "source": "/begrippen/maatschappelijke-ladder/",
    "target": "https://schoolwoorden.nl/begrip/maatschappelijke-ladder/"
  },
  {
    "line": "203",
    "status": "301",
    "source": "/begrippen/sociale-klasse/",
    "target": "https://schoolwoorden.nl/begrip/sociale-klasse/"
  },
  {
    "line": "204",
    "status": "301",
    "source": "/begrippen/sociale-mobiliteit/",
    "target": "https://schoolwoorden.nl/begrip/sociale-mobiliteit/"
  },
  {
    "line": "205",
    "status": "301",
    "source": "/begrippen/bedrijfscultuur/",
    "target": "https://schoolwoorden.nl/begrip/bedrijfscultuur/"
  },
  {
    "line": "206",
    "status": "301",
    "source": "/begrippen/werkverhoudingen/",
    "target": "https://schoolwoorden.nl/begrip/werkverhoudingen/"
  },
  {
    "line": "207",
    "status": "301",
    "source": "/begrippen/arbeidsvoorwaarden/",
    "target": "https://schoolwoorden.nl/begrip/arbeidsvoorwaarden/"
  },
  {
    "line": "208",
    "status": "301",
    "source": "/begrippen/medezeggenschap/",
    "target": "https://schoolwoorden.nl/begrip/medezeggenschap/"
  },
  {
    "line": "209",
    "status": "301",
    "source": "/begrippen/sociale-rol/",
    "target": "https://schoolwoorden.nl/begrip/sociale-rol/"
  },
  {
    "line": "210",
    "status": "301",
    "source": "/begrippen/rechtse-partijen/",
    "target": "https://schoolwoorden.nl/begrip/rechtse-partijen/"
  },
  {
    "line": "211",
    "status": "301",
    "source": "/begrippen/linkse-partijen/",
    "target": "https://schoolwoorden.nl/begrip/linkse-partijen/"
  },
  {
    "line": "212",
    "status": "301",
    "source": "/begrippen/betaald-werk/",
    "target": "https://schoolwoorden.nl/begrip/betaald-werk/"
  },
  {
    "line": "213",
    "status": "301",
    "source": "/begrippen/onbetaald-werk/",
    "target": "https://schoolwoorden.nl/begrip/onbetaald-werk/"
  },
  {
    "line": "214",
    "status": "301",
    "source": "/begrippen/vrijwilligers-werk/",
    "target": "https://schoolwoorden.nl/begrip/vrijwilligerswerk/"
  },
  {
    "line": "215",
    "status": "301",
    "source": "/begrippen/autoritair-leiderschap/",
    "target": "https://schoolwoorden.nl/begrip/autoritair-leiderschap/"
  },
  {
    "line": "216",
    "status": "301",
    "source": "/begrippen/consulterend-leiderschap/",
    "target": "https://schoolwoorden.nl/begrip/consulterend-leiderschap/"
  },
  {
    "line": "217",
    "status": "301",
    "source": "/begrippen/democratisch-leiderschap/",
    "target": "https://schoolwoorden.nl/begrip/democratisch-leiderschap/"
  },
  {
    "line": "218",
    "status": "301",
    "source": "/begrippen/laissez-faire-leiderschap/",
    "target": "https://schoolwoorden.nl/begrip/laissez-faire-leiderschap/"
  },
  {
    "line": "219",
    "status": "301",
    "source": "/begrippen/verzorgingsstaat/",
    "target": "https://schoolwoorden.nl/begrip/verzorgingsstaat/"
  },
  {
    "line": "220",
    "status": "301",
    "source": "/begrippen/vergrijzing/",
    "target": "https://schoolwoorden.nl/begrip/vergrijzing/"
  },
  {
    "line": "221",
    "status": "301",
    "source": "/begrippen/nachtwakersstaat/",
    "target": "https://schoolwoorden.nl/begrip/nachtwakersstaat/"
  },
  {
    "line": "222",
    "status": "301",
    "source": "/begrippen/participatiesamenleving/",
    "target": "https://schoolwoorden.nl/begrip/participatiesamenleving/"
  },
  {
    "line": "223",
    "status": "301",
    "source": "/begrippen/arbeidsomstandigheden/",
    "target": "https://schoolwoorden.nl/begrip/arbeidsomstandigheden/"
  },
  {
    "line": "224",
    "status": "301",
    "source": "/begrippen/arboregels/",
    "target": "https://schoolwoorden.nl/begrip/arboregels/"
  },
  {
    "line": "225",
    "status": "301",
    "source": "/begrippen/arbeidsinspectie/",
    "target": "https://schoolwoorden.nl/begrip/arbeidsinspectie/"
  },
  {
    "line": "226",
    "status": "301",
    "source": "/begrippen/medezeggenschapsraad/",
    "target": "https://schoolwoorden.nl/begrip/medezeggenschapsraad/"
  },
  {
    "line": "227",
    "status": "301",
    "source": "/begrippen/ondernemingsraad/",
    "target": "https://schoolwoorden.nl/begrip/ondernemingsraad/"
  },
  {
    "line": "228",
    "status": "301",
    "source": "/begrippen/werknemersverzekeringen/",
    "target": "https://schoolwoorden.nl/begrip/werknemersverzekeringen/"
  },
  {
    "line": "229",
    "status": "301",
    "source": "/begrippen/volksverzekeringen/",
    "target": "https://schoolwoorden.nl/begrip/volksverzekering/"
  },
  {
    "line": "230",
    "status": "301",
    "source": "/begrippen/sociale-verzekeringen/",
    "target": "https://schoolwoorden.nl/begrip/sociale-verzekeringen/"
  },
  {
    "line": "231",
    "status": "301",
    "source": "/begrippen/sociale-voorzieningen/",
    "target": "https://schoolwoorden.nl/begrip/sociale-voorzieningen/"
  },
  {
    "line": "232",
    "status": "301",
    "source": "/begrippen/arbeidsverdeling/",
    "target": "https://schoolwoorden.nl/begrip/arbeidsverdeling/"
  },
  {
    "line": "233",
    "status": "301",
    "source": "/begrippen/werkgeversorganisatie/",
    "target": "https://schoolwoorden.nl/begrip/werkgeversorganisatie/"
  },
  {
    "line": "234",
    "status": "301",
    "source": "/begrippen/collectieve-arbeidsovereenkomst/",
    "target": "https://schoolwoorden.nl/begrip/collectieve-arbeidsovereenkomst/"
  },
  {
    "line": "235",
    "status": "301",
    "source": "/begrippen/sociale-partners/",
    "target": "https://schoolwoorden.nl/begrip/sociale-partners/"
  },
  {
    "line": "236",
    "status": "301",
    "source": "/begrippen/pressiemiddelen/",
    "target": "https://schoolwoorden.nl/begrip/pressiemiddelen/"
  },
  {
    "line": "237",
    "status": "301",
    "source": "/begrippen/beroepsbevolking/",
    "target": "https://schoolwoorden.nl/begrip/beroepsbevolking/"
  },
  {
    "line": "238",
    "status": "301",
    "source": "/begrippen/conjuncturele-werkloosheid/",
    "target": "https://schoolwoorden.nl/begrip/conjuncturele-werkloosheid/"
  },
  {
    "line": "239",
    "status": "301",
    "source": "/begrippen/structurele-werkloosheid/",
    "target": "https://schoolwoorden.nl/begrip/structurele-werkloosheid/"
  },
  {
    "line": "240",
    "status": "301",
    "source": "/begrippen/frictiewerkloosheid/",
    "target": "https://schoolwoorden.nl/begrip/frictiewerkloosheid/"
  },
  {
    "line": "241",
    "status": "301",
    "source": "/begrippen/mechanisering/",
    "target": "https://schoolwoorden.nl/begrip/mechanisering/"
  },
  {
    "line": "242",
    "status": "301",
    "source": "/begrippen/automatisering/",
    "target": "https://schoolwoorden.nl/begrip/automatisering/"
  },
  {
    "line": "243",
    "status": "301",
    "source": "/begrippen/informatisering/",
    "target": "https://schoolwoorden.nl/begrip/informatisering/"
  },
  {
    "line": "244",
    "status": "301",
    "source": "/begrippen/positieve-discriminatie/",
    "target": "https://schoolwoorden.nl/begrip/positieve-discriminatie/"
  },
  {
    "line": "245",
    "status": "301",
    "source": "/begrippen/gedrukte-media/",
    "target": "https://schoolwoorden.nl/begrip/gedrukte-media/"
  },
  {
    "line": "246",
    "status": "301",
    "source": "/begrippen/audiovisuele-media/",
    "target": "https://schoolwoorden.nl/begrip/audiovisuele-media/"
  },
  {
    "line": "247",
    "status": "301",
    "source": "/begrippen/interactieve-media/",
    "target": "https://schoolwoorden.nl/begrip/interactieve-media/"
  },
  {
    "line": "248",
    "status": "301",
    "source": "/begrippen/bindende-functie/",
    "target": "https://schoolwoorden.nl/begrip/bindende-functie/"
  },
  {
    "line": "249",
    "status": "301",
    "source": "/begrippen/educatieve-functie/",
    "target": "https://schoolwoorden.nl/begrip/educatieve-functie/"
  },
  {
    "line": "250",
    "status": "301",
    "source": "/begrippen/informerende-functie/",
    "target": "https://schoolwoorden.nl/begrip/informatiefunctie/"
  },
  {
    "line": "251",
    "status": "301",
    "source": "/begrippen/socialiserende-functie/",
    "target": "https://schoolwoorden.nl/begrip/socialiserende-functie/"
  },
  {
    "line": "252",
    "status": "301",
    "source": "/begrippen/agenda-functie/",
    "target": "https://schoolwoorden.nl/begrip/agendafunctie/"
  },
  {
    "line": "253",
    "status": "301",
    "source": "/begrippen/commentaar-functie/",
    "target": "https://schoolwoorden.nl/begrip/commentaarfunctie/"
  },
  {
    "line": "254",
    "status": "301",
    "source": "/begrippen/opinierende-functie/",
    "target": "https://schoolwoorden.nl/begrip/opinierende-functie/"
  },
  {
    "line": "255",
    "status": "301",
    "source": "/begrippen/spreekbuisfunctie/",
    "target": "https://schoolwoorden.nl/begrip/spreekbuisfunctie/"
  },
  {
    "line": "256",
    "status": "301",
    "source": "/begrippen/publieke-opinie/",
    "target": "https://schoolwoorden.nl/begrip/publieke-opinie/"
  },
  {
    "line": "257",
    "status": "301",
    "source": "/begrippen/democratische-besluitvorming/",
    "target": "https://schoolwoorden.nl/begrip/democratische-besluitvorming/"
  },
  {
    "line": "258",
    "status": "301",
    "source": "/begrippen/cultuuroverdracht/",
    "target": "https://schoolwoorden.nl/begrip/cultuuroverdracht/"
  },
  {
    "line": "259",
    "status": "301",
    "source": "/begrippen/pluriformiteit/",
    "target": "https://schoolwoorden.nl/begrip/pluriformiteit/"
  },
  {
    "line": "260",
    "status": "301",
    "source": "/begrippen/theorie-selectieve-perceptie/",
    "target": "https://schoolwoorden.nl/begrip/theorie-van-de-selectieve-perceptie"
  },
  {
    "line": "261",
    "status": "301",
    "source": "/begrippen/selectieve-perceptie/",
    "target": "https://schoolwoorden.nl/begrip/selectieve-perceptie/"
  },
  {
    "line": "262",
    "status": "301",
    "source": "/begrippen/media-als-betekenisverlener/",
    "target": "https://schoolwoorden.nl/begrip/media-als-betekenisverlener/"
  },
  {
    "line": "263",
    "status": "301",
    "source": "/begrippen/inburgeren/",
    "target": "https://schoolwoorden.nl/begrip/inburgeren/"
  },
  {
    "line": "264",
    "status": "301",
    "source": "/begrippen/cultuur/",
    "target": "https://schoolwoorden.nl/begrip/cultuur/"
  },
  {
    "line": "265",
    "status": "301",
    "source": "/begrippen/ik-cultuur/",
    "target": "https://schoolwoorden.nl/begrip/ik-cultuur/"
  },
  {
    "line": "266",
    "status": "301",
    "source": "/begrippen/wij-cultuur/",
    "target": "https://schoolwoorden.nl/begrip/wij-cultuur/"
  },
  {
    "line": "267",
    "status": "301",
    "source": "/begrippen/kapitalisme/",
    "target": "https://schoolwoorden.nl/begrip/kapitalisme/"
  },
  {
    "line": "268",
    "status": "301",
    "source": "/begrippen/secularisatie/",
    "target": "https://schoolwoorden.nl/begrip/secularisatie/"
  },
  {
    "line": "269",
    "status": "301",
    "source": "/begrippen/toelatingsbeleid/",
    "target": "https://schoolwoorden.nl/begrip/toelatingsbeleid/"
  },
  {
    "line": "270",
    "status": "301",
    "source": "/begrippen/immigratiebeleid/",
    "target": "https://schoolwoorden.nl/begrip/immigratiebeleid/"
  },
  {
    "line": "271",
    "status": "301",
    "source": "/begrippen/visum/",
    "target": "https://schoolwoorden.nl/begrip/visum/"
  },
  {
    "line": "272",
    "status": "301",
    "source": "/begrippen/verblijfsvergunning/",
    "target": "https://schoolwoorden.nl/begrip/verblijfsvergunning/"
  },
  {
    "line": "273",
    "status": "301",
    "source": "/begrippen/integratiebeleid/",
    "target": "https://schoolwoorden.nl/begrip/integratiebeleid/"
  },
  {
    "line": "274",
    "status": "301",
    "source": "/begrippen/integratie/",
    "target": "https://schoolwoorden.nl/begrip/integreren/"
  },
  {
    "line": "275",
    "status": "301",
    "source": "/begrippen/gezinshereniging/",
    "target": "https://schoolwoorden.nl/begrip/gezinshereniging/"
  },
  {
    "line": "276",
    "status": "301",
    "source": "/begrippen/repatrieren/",
    "target": "https://schoolwoorden.nl/begrip/repatrieren/"
  },
  {
    "line": "277",
    "status": "301",
    "source": "/begrippen/kolonie/",
    "target": "https://schoolwoorden.nl/begrip/kolonien/"
  },
  {
    "line": "278",
    "status": "301",
    "source": "/begrippen/moederland/",
    "target": "https://schoolwoorden.nl/begrip/moederland/"
  },
  {
    "line": "279",
    "status": "301",
    "source": "/begrippen/vaderland/",
    "target": "https://schoolwoorden.nl/begrip/vaderland/"
  },
  {
    "line": "280",
    "status": "301",
    "source": "/begrippen/machtiging-tot-voorlopig-verblijf/",
    "target": "https://schoolwoorden.nl/begrip/machtiging-tot-voorlopig-verblijf/"
  },
  {
    "line": "281",
    "status": "301",
    "source": "/begrippen/asielzoeker/",
    "target": "https://schoolwoorden.nl/begrip/asielzoeker/"
  },
  {
    "line": "282",
    "status": "301",
    "source": "/begrippen/verenigde-naties/",
    "target": "https://schoolwoorden.nl/begrip/verenigde-naties/"
  },
  {
    "line": "283",
    "status": "301",
    "source": "/begrippen/vluchtelingenverdrag-van-geneve/",
    "target": "https://schoolwoorden.nl/begrip/vluchtelingenverdrag-van-geneve/"
  },
  {
    "line": "284",
    "status": "301",
    "source": "/begrippen/verdrag-van-maastricht/",
    "target": "https://schoolwoorden.nl/begrip/verdrag-van-maastricht/"
  },
  {
    "line": "285",
    "status": "301",
    "source": "/begrippen/multicultureel-drama/",
    "target": "https://schoolwoorden.nl/begrip/multicultureel-drama/"
  },
  {
    "line": "286",
    "status": "301",
    "source": "/begrippen/autochtoon/",
    "target": "https://schoolwoorden.nl/begrip/autochtoon/"
  },
  {
    "line": "287",
    "status": "301",
    "source": "/begrippen/allochtoon/",
    "target": "https://schoolwoorden.nl/begrip/allochtoon/"
  },
  {
    "line": "288",
    "status": "301",
    "source": "/begrippen/discriminatie/",
    "target": "https://schoolwoorden.nl/begrip/discriminatie/"
  },
  {
    "line": "289",
    "status": "301",
    "source": "/begrippen/racisme/",
    "target": "https://schoolwoorden.nl/begrip/racisme/"
  },
  {
    "line": "290",
    "status": "301",
    "source": "/begrippen/niet-westerse-cultuur/",
    "target": "https://schoolwoorden.nl/begrip/niet-westerse-cultuur/"
  },
  {
    "line": "291",
    "status": "301",
    "source": "/begrippen/westerse-cultuur/",
    "target": "https://schoolwoorden.nl/begrip/westerse-cultuur/"
  },
  {
    "line": "292",
    "status": "301",
    "source": "/begrippen/vooroordeel/",
    "target": "https://schoolwoorden.nl/begrip/vooroordeel/"
  },
  {
    "line": "293",
    "status": "301",
    "source": "/begrippen/migrant/",
    "target": "https://schoolwoorden.nl/begrip/migranten/"
  },
  {
    "line": "294",
    "status": "301",
    "source": "/begrippen/universele-verklaring-rechten-mens/",
    "target": "https://schoolwoorden.nl/begrip/universele-verklaring-van-de-rechten-van-de-mens/"
  },
  {
    "line": "295",
    "status": "301",
    "source": "/begrippen/recht-van-vragen/",
    "target": "https://schoolwoorden.nl/begrip/recht-van-vragen/"
  },
  {
    "line": "296",
    "status": "301",
    "source": "/begrippen/recht-van-interpellatie/",
    "target": "https://schoolwoorden.nl/begrip/recht-van-interpellatie/"
  },
  {
    "line": "297",
    "status": "301",
    "source": "/begrippen/vreemdelingenidentiteisbewijs/",
    "target": "https://schoolwoorden.nl/begrip/vreemdelingenidentiteitsbewijs"
  },
  {
    "line": "298",
    "status": "301",
    "source": "/begrippen/sociale-ongelijkheid/",
    "target": "https://schoolwoorden.nl/begrip/sociale-ongelijkheid/"
  },
  {
    "line": "299",
    "status": "301",
    "source": "/begrippen/eigenrichting/",
    "target": "https://schoolwoorden.nl/begrip/eigenrichting/"
  },
  {
    "line": "300",
    "status": "301",
    "source": "/begrippen/vermogenscriminaliteit/",
    "target": "https://schoolwoorden.nl/begrip/vermogenscriminaliteit/"
  },
  {
    "line": "301",
    "status": "301",
    "source": "/begrippen/stereotypen/",
    "target": "https://schoolwoorden.nl/begrip/stereotype/"
  },
  {
    "line": "302",
    "status": "301",
    "source": "/begrippen/minderheidskabinet/",
    "target": "https://schoolwoorden.nl/begrip/minderheidskabinet/"
  },
  {
    "line": "303",
    "status": "301",
    "source": "/begrippen/amusementsfunctie/",
    "target": "https://schoolwoorden.nl/begrip/amusementsfunctie/"
  },
  {
    "line": "304",
    "status": "301",
    "source": "/begrippen/burgerinitiatief/",
    "target": "https://schoolwoorden.nl/begrip/burgerinitiatief/"
  },
  {
    "line": "305",
    "status": "301",
    "source": "/begrippen/portefeuille/",
    "target": "https://schoolwoorden.nl/begrip/portefeuille/"
  },
  {
    "line": "306",
    "status": "301",
    "source": "/begrippen/vakbond/",
    "target": "https://schoolwoorden.nl/begrip/vakbond/"
  },
  {
    "line": "307",
    "status": "301",
    "source": "/begrippen/xenofobie/",
    "target": "https://schoolwoorden.nl/begrip/xenofobie/"
  },
  {
    "line": "308",
    "status": "301",
    "source": "/begrippen/hechentnis/",
    "target": "https://schoolwoorden.nl/begrip/hechtenis/"
  },
  {
    "line": "309",
    "status": "301",
    "source": "/begrippen/vonnis/",
    "target": "https://schoolwoorden.nl/begrip/vonnis/"
  },
  {
    "line": "310",
    "status": "301",
    "source": "/begrippen/fouilleren/",
    "target": "https://schoolwoorden.nl/begrip/fouilleren/"
  },
  {
    "line": "311",
    "status": "301",
    "source": "/begrippen/advocaat/",
    "target": "https://schoolwoorden.nl/begrip/advocaat/"
  },
  {
    "line": "312",
    "status": "301",
    "source": "/begrippen/vandalisme/",
    "target": "https://schoolwoorden.nl/begrip/vandalisme/"
  },
  {
    "line": "313",
    "status": "301",
    "source": "/begrippen/bureaucratie/",
    "target": "https://schoolwoorden.nl/begrip/bureaucratie/"
  },
  {
    "line": "314",
    "status": "301",
    "source": "/begrippen/socialisatie/",
    "target": "https://schoolwoorden.nl/begrip/socialisatie/"
  },
  {
    "line": "315",
    "status": "301",
    "source": "/begrippen/vergelding/",
    "target": "https://schoolwoorden.nl/begrip/vergelding/"
  },
  {
    "line": "316",
    "status": "301",
    "source": "/begrippen/terbeschikkingstelling-tbs/",
    "target": "https://schoolwoorden.nl/begrip/tbs/"
  },
  {
    "line": "317",
    "status": "301",
    "source": "/begrippen/seizoenwerkloosheid/",
    "target": "https://schoolwoorden.nl/begrip/seizoenswerkloosheid/"
  },
  {
    "line": "318",
    "status": "301",
    "source": "/begrippen/grondwet/",
    "target": "https://schoolwoorden.nl/begrip/grondwet/"
  },
  {
    "line": "319",
    "status": "301",
    "source": "/begrippen/oppositiepartijen/",
    "target": "https://schoolwoorden.nl/begrip/oppositiepartijen/"
  },
  {
    "line": "320",
    "status": "301",
    "source": "/begrippen/controlerende-functie/",
    "target": "https://schoolwoorden.nl/begrip/controle-of-waakhondfunctie/"
  },
  {
    "line": "321",
    "status": "301",
    "source": "/begrippen/jurisprudentie/",
    "target": "https://schoolwoorden.nl/begrip/jurisprudentie/"
  },
  {
    "line": "322",
    "status": "301",
    "source": "/begrippen/fracties/",
    "target": "https://schoolwoorden.nl/begrip/fractie/"
  },
  {
    "line": "323",
    "status": "301",
    "source": "/begrippen/jeugdstrafrecht/",
    "target": "https://schoolwoorden.nl/begrip/jeugdstrafrecht/"
  },
  {
    "line": "324",
    "status": "301",
    "source": "/begrippen/preventie/",
    "target": "https://schoolwoorden.nl/begrip/preventie/"
  },
  {
    "line": "325",
    "status": "301",
    "source": "/begrippen/propaganda/",
    "target": "https://schoolwoorden.nl/begrip/propaganda/"
  },
  {
    "line": "326",
    "status": "301",
    "source": "/begrippen/zwevende-kiezer/",
    "target": "https://schoolwoorden.nl/begrip/zwevende-kiezers/"
  },
  {
    "line": "327",
    "status": "301",
    "source": "/begrippen/repressie/",
    "target": "https://schoolwoorden.nl/begrip/repressie/"
  },
  {
    "line": "328",
    "status": "301",
    "source": "/begrippen/kiesrecht/",
    "target": "https://schoolwoorden.nl/begrip/kiesrecht/"
  },
  {
    "line": "329",
    "status": "301",
    "source": "/begrippen/emancipatiebeleid/",
    "target": "https://schoolwoorden.nl/begrip/emancipatiebeleid/"
  },
  {
    "line": "330",
    "status": "301",
    "source": "/begrippen/liberale-stroming/",
    "target": "https://schoolwoorden.nl/begrip/liberale-stroming/"
  },
  {
    "line": "331",
    "status": "301",
    "source": "/begrippen/socialistische-stroming/",
    "target": "https://schoolwoorden.nl/begrip/socialistische-stroming/"
  },
  {
    "line": "332",
    "status": "301",
    "source": "/begrippen/hoger-beroep/",
    "target": "https://schoolwoorden.nl/begrip/hoger-beroep/"
  },
  {
    "line": "333",
    "status": "301",
    "source": "/begrippen/cassatie/",
    "target": "https://schoolwoorden.nl/begrip/cassatie/"
  },
  {
    "line": "334",
    "status": "301",
    "source": "/begrippen/ecologische-stroming/",
    "target": "https://schoolwoorden.nl/begrip/ecologische-stroming/"
  },
  {
    "line": "335",
    "status": "301",
    "source": "/begrippen/politieke-functie/",
    "target": "https://schoolwoorden.nl/begrip/politieke-functie/"
  },
  {
    "line": "336",
    "status": "301",
    "source": "/begrippen/symbolische-functie/",
    "target": "https://schoolwoorden.nl/begrip/symbolische-functie/"
  },
  {
    "line": "337",
    "status": "301",
    "source": "/begrippen/ceremoniele-functie/",
    "target": "https://schoolwoorden.nl/begrip/ceremoniele-functie/"
  },
  {
    "line": "338",
    "status": "301",
    "source": "/begrippen/representatieve-functie/",
    "target": "https://schoolwoorden.nl/begrip/representatieve-functie/"
  },
  {
    "line": "339",
    "status": "301",
    "source": "/begrippen/minister/",
    "target": "https://schoolwoorden.nl/begrip/minister/"
  },
  {
    "line": "extra:legacy-examenstof",
    "status": "301",
    "source": "/politiekenbeleid-kerndoel1-1/",
    "target": "/examenstof/politiekenbeleid-kerndoel1-1/"
  },
  {
    "line": "extra:legacy-examenstof",
    "status": "301",
    "source": "/amv-kerndoel1/",
    "target": "/examenstof/amv-kerndoel1/"
  },
  {
    "line": "extra:legacy-examenstof",
    "status": "301",
    "source": "/ciminaliteitenrechtsstaat-kerndoel1/",
    "target": "/examenstof/criminaliteitenrechtsstaat-kerndoel1/"
  },
  {
    "line": "extra:removed-planning",
    "status": "301",
    "source": "/planning/",
    "target": "/examenstof/"
  },
  {
    "line": "extra:removed-planning",
    "status": "301",
    "source": "/planning/leerjaar3/",
    "target": "/examenstof/"
  },
  {
    "line": "extra:removed-planning",
    "status": "301",
    "source": "/planning/leerjaar4/",
    "target": "/examenstof/"
  },
  {
    "line": "extra:removed-kerndoelen-index",
    "status": "301",
    "source": "/kerndoelen/",
    "target": "/examenstof/"
  }
]